emmonite/__init__.py
emmonite/email.py
emmonite-0.1.3.dist-info/LICENSE
emmonite-0.1.3.dist-info/METADATA
emmonite-0.1.3.dist-info/WHEEL
emmonite-0.1.3.dist-info/top_level.txt
emmonite-0.1.3.dist-info/RECORD
