Metadata-Version: 2.1
Name: emmonite
Version: 0.1.3
Summary: Conjunto de librerias
Home-page: https://github.com/javierbahamondes/emmonite.git
Author: Javier Bahamondes
Author-email: jbahamondes@enorchile.cl
Classifier: Development Status :: 5 - Production/Stable
Classifier: Intended Audience :: Developers
Classifier: Topic :: Software Development :: Libraries
Classifier: License :: OSI Approved :: MIT License
Classifier: Programming Language :: Python :: 3
Classifier: Programming Language :: Python :: 3.6
Classifier: Programming Language :: Python :: 3.7
Classifier: Programming Language :: Python :: 3.8
Classifier: Programming Language :: Python :: 3.9
Classifier: Programming Language :: Python :: 3 :: Only
Classifier: Topic :: Communications :: Email
License-File: LICENSE
